auxiliares.v
`timescale 1ns / 1ps

//Guarda o endereço da instrução atual. Atualiza o endereço a cada subida do clock ou zera o endereço se o reset for acionado
module program_counter(clk, reset, pc_in, pc_out);
    input clk, reset;
    input [31:0] pc_in;
    output reg [31:0] pc_out;
    always @(posedge clk or posedge reset) begin
        if(reset) pc_out <= 32'b00;
        else pc_out <= pc_in;
    end
endmodule

//Calcula o endereço sequencial da próxima instrução na memória, somando 4 bytes ao endereço atual
module PCplus4(fromPC, nextPC);
    input [31:0] fromPC; output [31:0] nextPC;
    assign nextPC = fromPC+4;
endmodule

//Mux para ALUSrc: decide se a 2ª entrada da ULA será o valor de um registo (para add, or) ou o valor de um Imediato (para andi, lh, sh)
module mux1 (select1, a1, b1, mux1_out);
    input select1; input [31:0] a1, b1; output [31:0] mux1_out;
    assign mux1_out = (select1==1'b0) ? a1 : b1;
endmodule

//Mux para o PC: decide se a próxima instrução será a sequencial (PC+4) ou se será um endereço de salto (caso o bne seja verdadeiro)
module mux2 (select2, a2, b2, mux2_out);
    input select2; input [31:0] a2, b2; output [31:0] mux2_out;
    assign mux2_out = (select2==1'b0) ? a2 : b2;
endmodule

//Mux para o MemToReg: decide se o valor que vai ser guardado no Banco de Registos vem do resultado da ULA (ex: add) ou se vem de uma leitura da Memória de Dados (ex: lh)
module mux3 (select3, a3, b3, mux3_out);
    input select3; input [31:0] a3, b3; output [31:0] mux3_out;
    assign mux3_out = (select3==1'b0) ? a3 : b3;
endmodule

module AND_logic (branch, zero, and_out);
    input branch, zero; output and_out;
    assign and_out = branch & (~zero); // Os valores comparados na ULA têm de ser diferentes. Como a ULA emite zero = 1 quando os valores são iguais, nós invertemos o sinal (~zero). Assim, se a ULA diz que eles não são iguais (zero = 0), o ~zero vira 1, e o salto acontece (branch AND 1 = 1)
endmodule

//Este módulo é muito semelhante ao PCplus4, mas em vez de somar 4, ele soma valores variáveis para calcular o endereço exato para onde o código deve saltar
module adder(in_1, in_2, sum_out);
    input [31:0] in_1, in_2; output [31:0] sum_out;
    assign sum_out = in_1 + in_2;
endmodule

memorias.v
`timescale 1ns / 1ps

module instruction_mem(clk, reset, read_address, instruction_out);
    input clk, reset;
    input [31:0] read_address;
    output [31:0] instruction_out;
    
    reg [31:0] I_mem[63:0];

    assign instruction_out = I_mem[read_address >> 2];

endmodule


// Banco de Registradores

module reg_file (clk, reset, regWrite, rs1, rs2, rd, writeData, read_data1, read_data2);

    input clk, reset, regWrite;
    input [4:0] rs1, rs2, rd;
    input [31:0] writeData;
    output [31:0] read_data1, read_data2;
    integer k;
    reg [31:0] registers [31:0];

    // Só gravar quando o clock subir
    always @(posedge clk or posedge reset) begin
        if(reset) begin
            // Resetando pra limpar lixo de memoria
            for(k=0; k<32; k=k+1) registers[k] <= 32'b00;
        end else if (regWrite && rd != 0) begin
            // Grava apenas se o sinal de controle deixar e se não for para o x0
            registers[rd] <= writeData;
        end
    end

    assign read_data1 = registers[rs1];
    assign read_data2 = registers[rs2];

endmodule

module data_memory(clk, reset, memWrite, memRead, read_address, writeData, memData_out);
    input clk, reset, memWrite, memRead;
    input [31:0] read_address, writeData;
    output [31:0] memData_out;
    integer k;

    reg [31:0] Data_memory [63:0];
    wire [29:0] word_addr = read_address[31:2]; // Ajustando o endereço
    // Escreve na subida do clock
    always @(posedge clk or posedge reset) begin
        if(reset) begin
            for(k=0; k<64; k=k+1) Data_memory[k] <= 32'b00;
        end else if (memWrite) begin
            Data_memory[word_addr][15:0] <= writeData[15:0];
        end
    end

    wire [15:0] halfword = Data_memory[word_addr][15:0];
    // Se memRead estiver ativo pega os 16bits e extende o sinal (duplica o bit mais significagtivo) pra ser 32bits 
    assign memData_out = (memRead) ? { {16{halfword[15]}}, halfword } : 32'b00;
endmodule

ALU.v
`timescale 1ns / 1ps

//Responsavel por executar todas as operacoes matematicas e logicas e testar condicoes de salto
module ALU(A, B, control_in, ALU_result, zero);
    input [31:0] A, B;
    input [3:0] control_in;
    output reg zero; //É uma flag de 1 bit. Ela serve para ver se no caso do bne se os valores comparados são iguais.
    output reg [31:0] ALU_result;

    always @(*) begin
        case (control_in)
            4'b0000: begin zero <= 0; ALU_result <= A & B; end // ANDI
            4'b0001: begin zero <= 0; ALU_result <= A | B; end // OR
            4'b0010: begin zero <= 0; ALU_result <= A + B; end // ADD / LH / SH
            4'b0011: begin zero <= 0; ALU_result <= A << B[4:0]; end // SLL
            4'b0110: begin if(A==B) zero <= 1; else zero <= 0; ALU_result <= A - B; end // BNE (Usa sub para comparar)
            default: begin zero <= 0; ALU_result <= 32'b0; end
        endcase
    end
endmodule

controle.v
`timescale 1ns / 1ps

//Este módulo olha para opcode e decide o caminho dos dados
module unidadeControle(instruction, branch, memRead, memToReg, ALUop, memWrite, ALUSrc, regWrite);
    input [6:0] instruction;
    output reg branch, memRead, memToReg, memWrite, ALUSrc, regWrite;
    output reg [1:0] ALUop;

    always @(*) begin 
        case(instruction)
            7'b0110011 : {ALUSrc, memToReg, regWrite, memRead, memWrite, branch, ALUop} <= 8'b001000_10; // Tipo-R (ADD, OR, SLL)
            7'b0000011 : {ALUSrc, memToReg, regWrite, memRead, memWrite, branch, ALUop} <= 8'b111100_00; // LH
            7'b0100011 : {ALUSrc, memToReg, regWrite, memRead, memWrite, branch, ALUop} <= 8'b100010_00; // SH
            7'b1100011 : {ALUSrc, memToReg, regWrite, memRead, memWrite, branch, ALUop} <= 8'b000001_01; // BNE
            7'b0010011 : {ALUSrc, memToReg, regWrite, memRead, memWrite, branch, ALUop} <= 8'b101000_10; // ANDI colocámos ALUop = 10, pois a ULA percebe que tem de ler o funct3 para saber que a operação não é de soma, mas sim um AND
            default    : {ALUSrc, memToReg, regWrite, memRead, memWrite, branch, ALUop} <= 8'b000000_00;
        endcase
    end
endmodule

//Pega a instrução recebida da unidadeControle. Utiliza o sinal ALUop em conjunto com o campo funct3 da instrução para determinar o código exato de 4 bits que dirá à ULA a operação matemática a executar
module ALU_Control(ALUop, funct7, funct3, control_out);
    input funct7;
    input [2:0] funct3;
    input [1:0] ALUop;
    output reg [3:0] control_out;

    always @(*) begin
        case(ALUop)
            2'b00: control_out <= 4'b0010; // Load/Store usa Add
            2'b01: control_out <= 4'b0110; // Branch usa Sub para comparar
            2'b10: begin 
                case(funct3)
                    3'b000: control_out <= 4'b0010; // ADD
                    3'b110: control_out <= 4'b0001; // OR
                    3'b001: control_out <= 4'b0011; // SLL
                    3'b111: control_out <= 4'b0000; // ANDI
                    default: control_out <= 4'b0010;
                endcase
            end
            default: control_out <= 4'b0010;
        endcase
    end
endmodule

//Pega os imediatos de dentro da instrução de 32 bits. Como a posição dos bits varia conforme o tipo da instrução (Tipo-I, Tipo-S, Tipo-B), este módulo remonta o número e realiza a extensão de sinal para 32 bits.
module immConfig (opcode, instruction, immExt);
    input [6:0] opcode;
    input [31:0] instruction;
    output reg [31:0] immExt;

    always @(*) begin
        case(opcode)
            7'b0000011 : immExt <= {{20{instruction[31]}}, instruction[31:20]}; // LH
            7'b0010011 : immExt <= {{20{instruction[31]}}, instruction[31:20]}; // ANDI 
            7'b0100011 : immExt <= {{20{instruction[31]}}, instruction[31:25], instruction[11:7]}; // SH
            7'b1100011 : immExt <= {{19{instruction[31]}}, instruction[31], instruction[30:25], instruction[11:8], 1'b0}; // BNE
            default    : immExt <= 32'b0;
        endcase
    end
endmodule

top .v
`timescale 1ns / 1ps

module top(clk, reset);
    input clk, reset;
    
    // Fios que levam os dados de 32 bits de um bloco pro outro (Barramentos)
    wire [31:0] pc_top, instruction_top, rd1_top, rd2_top, immExt_top, mux1_top, sum_out_top, nextPC_top, PCin_top, address_top, memData_top, writeBack_top;
    
    // Flags e linhas de controle que ativam ou desativam as paradas nos blocos
    wire regWrite_top, ALUSrc_top, zero_top, branch_top, select2_top, memToReg_top, memWrite_top, memRead_top;
    wire [1:0] ALUop_top; 
    wire [3:0] control_top;

    // Fetch 
    program_counter pc(.clk(clk), .reset(reset), .pc_in(PCin_top), .pc_out(pc_top));
    
    // Somador que anda o PC de 4 em 4 bytes ir pra próxima instrução
    PCplus4 pc_adder(.fromPC(pc_top), .nextPC(nextPC_top));

    // Vai lá na Instruction Memory e pega o código binário da instrução atual
    instruction_mem Inst_mem(.clk(clk), .reset(reset), .read_address(pc_top), .instruction_out(instruction_top));

    // Decode
    // Banco de registradores: lê da instrução (rs1, rs2) e se regWrite = 1, salva o resultado em rd
    reg_file registerFile(.clk(clk), .reset(reset), .regWrite(regWrite_top), .rs1(instruction_top[19:15]), .rs2(instruction_top[24:20]), .rd(instruction_top[11:7]), .writeData(writeBack_top), .read_data1(rd1_top), .read_data2(rd2_top));
    
    // Estende o sinal pra virar um número de 32 bits (Imediato)
    immConfig immConfig(.opcode(instruction_top[6:0]), .instruction(instruction_top), .immExt(immExt_top));

    // Control
    unidadeControle unidadeControle(.instruction(instruction_top[6:0]), .branch(branch_top), .memRead(memRead_top), .memToReg(memToReg_top), .ALUop(ALUop_top), .memWrite(memWrite_top), .ALUSrc(ALUSrc_top), .regWrite(regWrite_top));

    // Decide qual operação vai fazer a ALU Control
    ALU_Control ALU_Control(.ALUop(ALUop_top), .funct7(instruction_top[30]), .funct3(instruction_top[14:12]), .control_out(control_top));

    // Roda a ALU
    ALU ALU(.A(rd1_top), .B(mux1_top), .control_in(control_top), .ALU_result(address_top), .zero(zero_top));

    // Mux da ALU para escolher se o segundo vai ser o registrador ou imediato
    mux1 ALU_mux(.select1(ALUSrc_top), .a1(rd2_top), .b1(immExt_top), .mux1_out(mux1_top));

    // ADD do BRANCH
    adder adder(.in_1(pc_top), .in_2(immExt_top), .sum_out(sum_out_top));

    // AND do BRANCH com o ZERO da ALU
    AND_logic AND_logic(.branch(branch_top), .zero(zero_top), .and_out(select2_top));
    
    // Mux do PC para definir se o PC vai pro próximo que é (PC+4) ou se pula pro endereço do BRANCH
    mux2 adder_mux(.select2(select2_top), .a2(nextPC_top), .b2(sum_out_top), .mux2_out(PCin_top));


    // Memoria usada no LOAD ou STORE
    data_memory data_mem(.clk(clk), .reset(reset), .memWrite(memWrite_top), .memRead(memRead_top), .read_address(address_top), .writeData(rd2_top), .memData_out(memData_top));
    
    // Mux final para escolher se o que vai voltar pro registrador veio da conta da ALU ou veio da memória
    mux3 mem_mux(.select3(memToReg_top), .a3(address_top), .b3(memData_top), .mux3_out(writeBack_top));
endmodule

tb_top.v
`timescale 1ns / 1ps

module tb_top();
    reg clk;
    reg reset;
    integer i;
    // Inicializando processador do top.v
    top uut (.clk(clk), .reset(reset));


    always #5 clk = ~clk;

    initial begin
        
        $dumpfile("wave.vcd");    // Nome do arquivo de onda 
        $dumpvars(0, tb_top);    

        // Reseta pra limpar lixo dos registradores
        clk = 0;
        reset = 1;  
        
        #12;
        reset = 0; 
        
        // Carrega os arquivos txt da memória
        // Feito após o reset para que o laço da memória não o apague.
        $readmemb("programa_bin.txt", uut.Inst_mem.I_mem);
        $readmemb("registradores.txt", uut.registerFile.registers);
        $readmemb("memoria.txt", uut.data_mem.Data_memory);

        $display("======= INICIO DA SIMULACAO CAMINHO DE DADOS (GRUPO 17) =======");
        
        #250;
        
        $display("\n=== ESTADO FINAL DOS 32 REGISTRADORES ===");
        for (i = 0; i < 32; i = i + 1) begin
            $display("Registrador [x%2d]: %d", i, uut.registerFile.registers[i]);
        end
        
        $display("\n=== PRIMEIRAS 32 POSICOES DA MEMORIA DE DADOS ===");
        for (i = 0; i < 32; i = i + 1) begin
            $display("Memoria Endereco [%2d]: %d", i * 4, uut.data_mem.Data_memory[i]);
        end

        $display("\n======= FIM DA SIMULACAO =======");
        $finish;
    end
endmodule

wave.vcd
$date
	Wed May 27 07:19:26 2026
$end
$version
	Icarus Verilog
$end
$timescale
	1ps
$end
$scope module tb_top $end
$var reg 1 ! clk $end
$var reg 1 " reset $end
$var integer 32 # i [31:0] $end
$scope module uut $end
$var wire 1 ! clk $end
$var wire 1 " reset $end
$var wire 1 $ zero_top $end
$var wire 32 % writeBack_top [31:0] $end
$var wire 32 & sum_out_top [31:0] $end
$var wire 1 ' select2_top $end
$var wire 1 ( regWrite_top $end
$var wire 32 ) rd2_top [31:0] $end
$var wire 32 * rd1_top [31:0] $end
$var wire 32 + pc_top [31:0] $end
$var wire 32 , nextPC_top [31:0] $end
$var wire 32 - mux1_top [31:0] $end
$var wire 1 . memWrite_top $end
$var wire 1 / memToReg_top $end
$var wire 1 0 memRead_top $end
$var wire 32 1 memData_top [31:0] $end
$var wire 32 2 instruction_top [31:0] $end
$var wire 32 3 immExt_top [31:0] $end
$var wire 4 4 control_top [3:0] $end
$var wire 1 5 branch_top $end
$var wire 32 6 address_top [31:0] $end
$var wire 32 7 PCin_top [31:0] $end
$var wire 2 8 ALUop_top [1:0] $end
$var wire 1 9 ALUSrc_top $end
$scope module ALU $end
$var wire 4 : control_in [3:0] $end
$var wire 32 ; B [31:0] $end
$var wire 32 < A [31:0] $end
$var reg 32 = ALU_result [31:0] $end
$var reg 1 $ zero $end
$upscope $end
$scope module ALU_Control $end
$var wire 3 > funct3 [2:0] $end
$var wire 1 ? funct7 $end
$var wire 2 @ ALUop [1:0] $end
$var reg 4 A control_out [3:0] $end
$upscope $end
$scope module ALU_mux $end
$var wire 1 9 select1 $end
$var wire 32 B mux1_out [31:0] $end
$var wire 32 C b1 [31:0] $end
$var wire 32 D a1 [31:0] $end
$upscope $end
$scope module AND_logic $end
$var wire 1 ' and_out $end
$var wire 1 $ zero $end
$var wire 1 5 branch $end
$upscope $end
$scope module Inst_mem $end
$var wire 1 ! clk $end
$var wire 32 E instruction_out [31:0] $end
$var wire 1 " reset $end
$var wire 32 F read_address [31:0] $end
$upscope $end
$scope module adder $end
$var wire 32 G sum_out [31:0] $end
$var wire 32 H in_2 [31:0] $end
$var wire 32 I in_1 [31:0] $end
$upscope $end
$scope module adder_mux $end
$var wire 32 J b2 [31:0] $end
$var wire 1 ' select2 $end
$var wire 32 K mux2_out [31:0] $end
$var wire 32 L a2 [31:0] $end
$upscope $end
$scope module data_mem $end
$var wire 1 ! clk $end
$var wire 32 M read_address [31:0] $end
$var wire 1 " reset $end
$var wire 32 N writeData [31:0] $end
$var wire 30 O word_addr [29:0] $end
$var wire 1 . memWrite $end
$var wire 1 0 memRead $end
$var wire 32 P memData_out [31:0] $end
$var wire 16 Q halfword [15:0] $end
$var integer 32 R k [31:0] $end
$upscope $end
$scope module immConfig $end
$var wire 32 S instruction [31:0] $end
$var wire 7 T opcode [6:0] $end
$var reg 32 U immExt [31:0] $end
$upscope $end
$scope module mem_mux $end
$var wire 32 V a3 [31:0] $end
$var wire 32 W b3 [31:0] $end
$var wire 1 / select3 $end
$var wire 32 X mux3_out [31:0] $end
$upscope $end
$scope module pc $end
$var wire 1 ! clk $end
$var wire 32 Y pc_in [31:0] $end
$var wire 1 " reset $end
$var reg 32 Z pc_out [31:0] $end
$upscope $end
$scope module pc_adder $end
$var wire 32 [ fromPC [31:0] $end
$var wire 32 \ nextPC [31:0] $end
$upscope $end
$scope module registerFile $end
$var wire 1 ! clk $end
$var wire 5 ] rd [4:0] $end
$var wire 32 ^ read_data1 [31:0] $end
$var wire 32 _ read_data2 [31:0] $end
$var wire 1 " reset $end
$var wire 5 ` rs1 [4:0] $end
$var wire 5 a rs2 [4:0] $end
$var wire 32 b writeData [31:0] $end
$var wire 1 ( regWrite $end
$var integer 32 c k [31:0] $end
$upscope $end
$scope module unidadeControle $end
$var wire 7 d instruction [6:0] $end
$var reg 1 9 ALUSrc $end
$var reg 2 e ALUop [1:0] $end
$var reg 1 5 branch $end
$var reg 1 0 memRead $end
$var reg 1 / memToReg $end
$var reg 1 . memWrite $end
$var reg 1 ( regWrite $end
$upscope $end
$upscope $end
$upscope $end
$enddefinitions $end
$comment Show the parameter values. $end
$dumpall
$end
#0
$dumpvars
bx e
bx d
b100000 c
bx b
bx a
bx `
bx _
bx ^
bx ]
b100 \
b0 [
b0 Z
bx Y
bx X
bx W
bx V
bx U
bx T
bx S
b1000000 R
bx Q
bx P
bx O
bx N
bx M
b100 L
bx K
bx J
b0 I
bx H
bx G
b0 F
bx E
bx D
bx C
bx B
bx A
bx @
x?
bx >
bx =
bx <
bx ;
bx :
x9
bx 8
bx 7
bx 6
x5
bx 4
bx 3
bx 2
bx 1
x0
x/
x.
bx -
b100 ,
b0 +
bx *
bx )
x(
x'
bx &
bx %
x$
bx #
1"
0!
$end
#5000
b1000000 R
b100000 c
1!
#10000
0!
#12000
b111 %
b111 X
b111 b
b111 1
b111 P
b111 W
b111 Q
0'
b1 O
b100 7
b100 K
b100 Y
b100 -
b100 ;
b100 B
b10 4
b10 :
b10 A
19
1/
1(
10
0.
05
b0 8
b0 @
b0 e
b100 6
b100 =
b100 M
b100 V
0$
b100 &
b100 G
b100 J
b100 3
b100 C
b100 H
b100 U
b1 >
0?
b11 d
b11 T
b1 ]
b0 )
b0 D
b0 N
b0 _
b100 a
b0 *
b0 <
b0 ^
b0 `
b10000000001000010000011 2
b10000000001000010000011 E
b10000000001000010000011 S
0"
#15000
b111 %
b111 X
b111 b
b111 Q
b0 1
b0 P
b0 W
b1 O
b0 -
b0 ;
b0 B
09
0/
00
b10 8
b10 @
b10 e
b111 6
b111 =
b111 M
b111 V
b0 3
b0 C
b0 H
b0 U
b0 >
b110011 d
b110011 T
b10 ]
b0 a
b111 *
b111 <
b111 ^
b1 `
b1000 7
b1000 K
b1000 Y
b1000000100110011 2
b1000000100110011 E
b1000000100110011 S
b1000 ,
b1000 L
b1000 \
b100 &
b100 G
b100 J
b100 +
b100 F
b100 I
b100 Z
b100 [
1!
#20000
0!
#25000
b100 %
b100 X
b100 b
b100 6
b100 =
b100 M
b100 V
b11100 -
b11100 ;
b11100 B
b0 4
b0 :
b0 A
19
b11100 3
b11100 C
b11100 H
b11100 U
b111 >
b10011 d
b10011 T
b11 ]
b11100 a
b1100 7
b1100 K
b1100 Y
b1110000001111000110010011 2
b1110000001111000110010011 E
b1110000001111000110010011 S
b1100 ,
b1100 L
b1100 \
b100100 &
b100100 G
b100100 J
b1000 +
b1000 F
b1000 I
b1000 Z
b1000 [
1!
#30000
0!
#35000
b0 Q
b0 O
b11 %
b11 X
b11 b
b11 6
b11 =
b11 M
b11 V
b11 -
b11 ;
b11 B
b11 3
b11 C
b11 H
b11 U
b100 ]
b100 )
b100 D
b100 N
b100 _
b11 a
b10000 7
b10000 K
b10000 Y
b1100001111001000010011 2
b1100001111001000010011 E
b1100001111001000010011 S
b10000 ,
b10000 L
b10000 \
b1111 &
b1111 G
b1111 J
b1100 +
b1100 F
b1100 I
b1100 Z
b1100 [
1!
#40000
0!
#45000
b111 Q
b1 O
b111 %
b111 X
b111 b
b11 -
b11 ;
b11 B
b10 4
b10 :
b10 A
09
b111 6
b111 =
b111 M
b111 V
b0 3
b0 C
b0 H
b0 U
b0 >
b110011 d
b110011 T
b101 ]
b11 )
b11 D
b11 N
b11 _
b100 a
b100 *
b100 <
b100 ^
b11 `
b10100 7
b10100 K
b10100 Y
b10000011000001010110011 2
b10000011000001010110011 E
b10000011000001010110011 S
b10100 ,
b10100 L
b10100 \
b10000 &
b10000 G
b10000 J
b10000 +
b10000 F
b10000 I
b10000 Z
b10000 [
1!
#50000
0!
#55000
1$
b0 Q
0'
b0 O
b0 %
b0 X
b0 b
b110 4
b110 :
b110 A
0(
15
b1 8
b1 @
b1 e
b0 6
b0 =
b0 M
b0 V
b1001000 3
b1001000 C
b1001000 H
b1001000 U
b111 -
b111 ;
b111 B
b1 >
b1100011 d
b1100011 T
b1000 ]
b111 )
b111 D
b111 N
b111 _
b101 a
b111 *
b111 <
b111 ^
b1 `
b11000 7
b11000 K
b11000 Y
b100010100001001010001100011 2
b100010100001001010001100011 E
b100010100001001010001100011 S
b11000 ,
b11000 L
b11000 \
b1011100 &
b1011100 G
b1011100 J
b10100 +
b10100 F
b10100 I
b10100 Z
b10100 [
1!
#60000
0!
#65000
b111 Q
b1 O
b1 4
b1 :
b1 A
b111 %
b111 X
b111 b
1(
05
b10 8
b10 @
b10 e
b111 6
b111 =
b111 M
b111 V
0$
b0 3
b0 C
b0 H
b0 U
b11 -
b11 ;
b11 B
b110 >
b110011 d
b110011 T
b110 ]
b11 )
b11 D
b11 N
b11 _
b100 a
b100 *
b100 <
b100 ^
b11 `
b11100 7
b11100 K
b11100 Y
b10000011110001100110011 2
b10000011110001100110011 E
b10000011110001100110011 S
b11100 ,
b11100 L
b11100 \
b11000 &
b11000 G
b11000 J
b11000 +
b11000 F
b11000 I
b11000 Z
b11000 [
1!
#70000
0!
#75000
1$
b0 Q
b0 O
b0 %
b0 X
b0 b
b0 6
b0 =
b0 M
b0 V
0'
b110 4
b110 :
b110 A
0(
15
b1 8
b1 @
b1 e
b111000 3
b111000 C
b111000 H
b111000 U
b111 -
b111 ;
b111 B
b1 >
b1100011 d
b1100011 T
b11000 ]
b111 )
b111 D
b111 N
b111 _
b110 a
b111 *
b111 <
b111 ^
b1 `
b100000 7
b100000 K
b100000 Y
b10011000001001110001100011 2
b10011000001001110001100011 E
b10011000001001110001100011 S
b100000 ,
b100000 L
b100000 \
b1010100 &
b1010100 G
b1010100 J
b11100 +
b11100 F
b11100 I
b11100 Z
b11100 [
1!
#80000
0!
#85000
b0 Q
b0 O
b1 %
b1 X
b1 b
b1 6
b1 =
b1 M
b1 V
0$
b0 4
b0 :
b0 A
b1 -
b1 ;
b1 B
19
1(
05
b10 8
b10 @
b10 e
b1 3
b1 C
b1 H
b1 U
b111 >
b10011 d
b10011 T
b111 ]
b1 a
b100100 7
b100100 K
b100100 Y
b100001111001110010011 2
b100001111001110010011 E
b100001111001110010011 S
b100100 ,
b100100 L
b100100 \
b100001 &
b100001 G
b100001 J
b100000 +
b100000 F
b100000 I
b100000 Z
b100000 [
1!
#90000
0!
#95000
b11 O
b1110 %
b1110 X
b1110 b
b1110 6
b1110 =
b1110 M
b1110 V
b1 -
b1 ;
b1 B
b11 4
b11 :
b11 A
09
b0 3
b0 C
b0 H
b0 U
b1 >
b110011 d
b110011 T
b1000 ]
b1 )
b1 D
b1 N
b1 _
b111 a
b101000 7
b101000 K
b101000 Y
b11100001001010000110011 2
b11100001001010000110011 E
b11100001001010000110011 S
b101000 ,
b101000 L
b101000 \
b100100 &
b100100 G
b100100 J
b100100 +
b100100 F
b100100 I
b100100 Z
b100100 [
1!
#100000
0!
#105000
b0 4
b0 :
b0 A
19
b1110 6
b1110 =
b1110 M
b1110 V
b1111 3
b1111 C
b1111 H
b1111 U
b1111 -
b1111 ;
b1111 B
b111 >
b10011 d
b10011 T
b1001 ]
b0 )
b0 D
b0 N
b0 _
b1111 a
b1110 *
b1110 <
b1110 ^
b1000 `
b101100 7
b101100 K
b101100 Y
b111101000111010010010011 2
b111101000111010010010011 E
b111101000111010010010011 S
b101100 ,
b101100 L
b101100 \
b110111 &
b110111 G
b110111 J
b101000 +
b101000 F
b101000 I
b101000 Z
b101000 [
1!
#110000
0!
#115000
1$
b0 Q
b0 O
b0 %
b0 X
b0 b
b0 6
b0 =
b0 M
b0 V
0'
b1110 -
b1110 ;
b1110 B
b110 4
b110 :
b110 A
09
0(
15
b1 8
b1 @
b1 e
b11000 3
b11000 C
b11000 H
b11000 U
b1 >
b1100011 d
b1100011 T
b11000 ]
b1110 )
b1110 D
b1110 N
b1110 _
b1001 a
b110000 7
b110000 K
b110000 Y
b100101000001110001100011 2
b100101000001110001100011 E
b100101000001110001100011 S
b110000 ,
b110000 L
b110000 \
b1000100 &
b1000100 G
b1000100 J
b101100 +
b101100 F
b101100 I
b101100 Z
b101100 [
1!
#120000
0!
#125000
b10 4
b10 :
b10 A
b0 Q
b0 O
b0 %
b0 X
b0 b
19
1.
05
b0 8
b0 @
b0 e
b0 6
b0 =
b0 M
b0 V
0$
b0 3
b0 C
b0 H
b0 U
b0 -
b0 ;
b0 B
b100011 d
b100011 T
b0 ]
b111 )
b111 D
b111 N
b111 _
b1 a
b0 *
b0 <
b0 ^
b0 `
b110100 7
b110100 K
b110100 Y
b100000001000000100011 2
b100000001000000100011 E
b100000001000000100011 S
b110100 ,
b110100 L
b110100 \
b110000 &
b110000 G
b110000 J
b110000 +
b110000 F
b110000 I
b110000 Z
b110000 [
1!
#130000
0!
#135000
b111111111111111111111111111110 O
b11111111111111111111111111111001 %
b11111111111111111111111111111001 X
b11111111111111111111111111111001 b
b11111111111111111111111111111001 6
b11111111111111111111111111111001 =
b11111111111111111111111111111001 M
b11111111111111111111111111111001 V
b110 4
b110 :
b110 A
b111 -
b111 ;
b111 B
1'
09
0.
15
b1 8
b1 @
b1 e
b1100011 d
b1100011 T
b110100 7
b110100 K
b110100 Y
b100000001000001100011 2
b100000001000001100011 E
b100000001000001100011 S
bx Q
b111000 ,
b111000 L
b111000 \
b110100 &
b110100 G
b110100 J
b110100 +
b110100 F
b110100 I
b110100 Z
b110100 [
1!
#140000
0!
#145000
1!
#150000
0!
#155000
1!
#160000
0!
#165000
1!
#170000
0!
#175000
1!
#180000
0!
#185000
1!
#190000
0!
#195000
1!
#200000
0!
#205000
1!
#210000
0!
#215000
1!
#220000
0!
#225000
1!
#230000
0!
#235000
1!
#240000
0!
#245000
1!
#250000
0!
#255000
1!
#260000
0!
#262000
b100000 #
